teradata_mcp_server/__init__.py
teradata_mcp_server/__main__.py
teradata_mcp_server/server.py
teradata_mcp_server/utils.py
teradata_mcp_server/config/__init__.py
teradata_mcp_server/config/rag_config.yml
teradata_mcp_server/config/sql_opt_config.yml
teradata_mcp_server/tools/__init__.py
teradata_mcp_server/tools/evs_connect.py
teradata_mcp_server/tools/module_loader.py
teradata_mcp_server/tools/td_connect.py
teradata_mcp_server/tools/utils.py
teradata_mcp_server/tools/base/README.md
teradata_mcp_server/tools/base/__init__.py
teradata_mcp_server/tools/base/base_resources.py
teradata_mcp_server/tools/base/base_tools.py
teradata_mcp_server/tools/dba/README.md
teradata_mcp_server/tools/dba/__init__.py
teradata_mcp_server/tools/dba/dba_resources.py
teradata_mcp_server/tools/dba/dba_tools.py
teradata_mcp_server/tools/evs/README.md
teradata_mcp_server/tools/evs/__init__.py
teradata_mcp_server/tools/evs/evs_resources.py
teradata_mcp_server/tools/evs/evs_tools.py
teradata_mcp_server/tools/fs/README.md
teradata_mcp_server/tools/fs/__init__.py
teradata_mcp_server/tools/fs/fs_prompts.py
teradata_mcp_server/tools/fs/fs_resources.py
teradata_mcp_server/tools/fs/fs_tools.py
teradata_mcp_server/tools/fs/fs_utils.py
teradata_mcp_server/tools/qlty/README.md
teradata_mcp_server/tools/qlty/__init__.py
teradata_mcp_server/tools/qlty/qlty_resources.py
teradata_mcp_server/tools/qlty/qlty_tools.py
teradata_mcp_server/tools/rag/README.md
teradata_mcp_server/tools/rag/__init__.py
teradata_mcp_server/tools/rag/rag_resources.py
teradata_mcp_server/tools/rag/rag_tools.py
teradata_mcp_server/tools/sec/README.md
teradata_mcp_server/tools/sec/__init__.py
teradata_mcp_server/tools/sec/sec_resources.py
teradata_mcp_server/tools/sec/sec_tools.py
teradata_mcp_server/tools/sql_opt/README.md
teradata_mcp_server/tools/sql_opt/__init__.py
teradata_mcp_server/tools/sql_opt/sql_opt_resources.py
teradata_mcp_server/tools/sql_opt/sql_opt_tools.py
teradata_mcp_server/tools/tmpl/README.md
mseep_teradata_mcp_server-0.1.4.dist-info/METADATA
mseep_teradata_mcp_server-0.1.4.dist-info/WHEEL
mseep_teradata_mcp_server-0.1.4.dist-info/entry_points.txt
mseep_teradata_mcp_server-0.1.4.dist-info/licenses/LICENSE
mseep_teradata_mcp_server-0.1.4.dist-info/RECORD
